LICENSE.txt
MANIFEST.in
README.txt
setup.py
pcart_statistics/__init__.py
pcart_statistics/admin.py
pcart_statistics/apps.py
pcart_statistics/cms_plugins.py
pcart_statistics/forms.py
pcart_statistics/models.py
pcart_statistics/tasks.py
pcart_statistics/urls.py
pcart_statistics/utils.py
pcart_statistics/views.py
pcart_statistics.egg-info/PKG-INFO
pcart_statistics.egg-info/SOURCES.txt
pcart_statistics.egg-info/dependency_links.txt
pcart_statistics.egg-info/not-zip-safe
pcart_statistics.egg-info/requires.txt
pcart_statistics.egg-info/top_level.txt
pcart_statistics/locale/ru/LC_MESSAGES/django.mo
pcart_statistics/locale/ru/LC_MESSAGES/django.po
pcart_statistics/locale/uk/LC_MESSAGES/django.mo
pcart_statistics/locale/uk/LC_MESSAGES/django.po
pcart_statistics/migrations/0001_initial.py
pcart_statistics/migrations/0002_lastvisitedpluginmodel.py
pcart_statistics/migrations/__init__.py
pcart_statistics/templatetags/__init__.py
pcart_statistics/templatetags/pcart_statistics.py